cgmodels/__init__.py
cgmodels/exceptions.py
cgmodels/cg/__init__.py
cgmodels/cg/constants.py
cgmodels/crunchy/__init__.py
cgmodels/crunchy/metadata.py
cgmodels/demultiplex/__init__.py
cgmodels/demultiplex/sample_sheet.py
cgmodels/trailblazer/__init__.py
cgmodels/trailblazer/constants.py
tests/__init__.py
tests/conftest.py
tests/crunchy/__init__.py
tests/crunchy/conftest.py
tests/crunchy/test_crunchy_metadata_schema.py
tests/demultiplex/__init__.py
tests/demultiplex/test_validate_sample_sheet.py
cgmodels-0.11.0.dist-info/METADATA
cgmodels-0.11.0.dist-info/WHEEL
cgmodels-0.11.0.dist-info/top_level.txt
cgmodels-0.11.0.dist-info/RECORD
