Metadata-Version: 2.1
Name: cgmodels
Version: 0.11.0
Summary: UNKNOWN
Home-page: https://github.com/Clinical-Genomics/cgmodels
Author: Måns Magnusson
Author-email: mans.magnusson@scilifelab.se
License: UNKNOWN
Platform: UNKNOWN
Classifier: Programming Language :: Python :: 3.7
Classifier: License :: OSI Approved :: MIT License
Classifier: Operating System :: OS Independent
Requires-Dist: dataclasses
Requires-Dist: pydantic
Requires-Dist: typing-extensions
Requires-Dist: atomicwrites
Requires-Dist: attrs
Requires-Dist: colorama
Requires-Dist: coverage
Requires-Dist: importlib-metadata
Requires-Dist: more-itertools
Requires-Dist: packaging
Requires-Dist: pluggy
Requires-Dist: py
Requires-Dist: pyparsing
Requires-Dist: pytest
Requires-Dist: pytest-cov
Requires-Dist: wcwidth
Requires-Dist: zipp
